hub/__init__.py
hub/battery.py
hub/bluetooth.py
hub/button.py
hub/display.py
hub/motion.py
hub/port.py
hub/sound.py
hub/supervision.py
spike/__init__.py
spike/control.py
pyhub_stubs-0.0.2.dist-info/LICENSE
pyhub_stubs-0.0.2.dist-info/METADATA
pyhub_stubs-0.0.2.dist-info/WHEEL
pyhub_stubs-0.0.2.dist-info/top_level.txt
pyhub_stubs-0.0.2.dist-info/RECORD
