Metadata-Version: 2.1
Name: pyhub-stubs
Version: 0.0.2
Summary: Python API Stub for Lego® Spike Prime and LEGO® MINDSTORMS® Robot Inventor
Home-page: https://github.com/XenseEducation/pyhub-stubs
Author: Xense Education
Author-email: info@xense.net
License: MIT
Project-URL: Source, https://github.com/XenseEducation/pyhub-stubs
Keywords: lego,spike,prime,mindstorms
Classifier: Programming Language :: Python
Classifier: Programming Language :: Python :: 3
Classifier: Programming Language :: Python :: 3.6
Classifier: Programming Language :: Python :: 3.7
Classifier: Programming Language :: Python :: 3.8
Classifier: Programming Language :: Python :: 3.9
Classifier: Programming Language :: Python :: 3.10
Classifier: License :: OSI Approved :: MIT License
Classifier: Operating System :: OS Independent
Classifier: Intended Audience :: Developers
Classifier: Natural Language :: English
License-File: LICENSE
